Metadata-Version: 1.1
Name: icecream-only
Version: 0.0.1.6
Summary: icecream_only
Home-page: https://github.com/salabim/icecream_only
Author: Ruud van der Ham
Author-email: info@salabim.org
License: UNKNOWN
Download-URL: https://github.com/salabim/icecream_only
Keywords: property,addon
Platform: UNKNOWN
